{"users":[{"id":0,"name":{"firstName":"峻熙","lastName":"赖"},"info":{"phoneNumber":"566-89056021","address":{"city":"哲瀚沙市","zpiCode":"490388"}}},{"id":1,"name":{"firstName":"笑愚","lastName":"苏"},"info":{"phoneNumber":"906-10753709","address":{"city":"鸿煊门市","zpiCode":"802418"}}},{"id":2,"name":{"firstName":"明辉","lastName":"何"},"info":{"phoneNumber":"901-00226390","address":{"city":"安 黎阳市","zpiCode":"761373"}}},{"id":3,"name":{"firstName":"泽洋","lastName":"杜"},"info":{"phoneNumber":"525-72398788","address":{"city":"武 赖","zpiCode":"093923"}}},{"id":4,"name":{"firstName":"浩","lastName":"蒋"},"info":{"phoneNumber":"894-85792420","address":{"city":"衡 袁","zpiCode":"656445"}}},{"id":5,"name":{"firstName":"晓博","lastName":"龚"},"info":{"phoneNumber":"043-74015523","address":{"city":"罗沙市","zpiCode":"092524"}}},{"id":6,"name":{"firstName":"皓轩","lastName":"韦"},"info":{"phoneNumber":"959-05742158","address":{"city":"济 杜","zpiCode":"144133"}}},{"id":7,"name":{"firstName":"文博","lastName":"熊"},"info":{"phoneNumber":"844-33357156","address":{"city":"衡 陶","zpiCode":"490279"}}},{"id":8,"name":{"firstName":"健柏","lastName":"何"},"info":{"phoneNumber":"832-87826588","address":{"city":"吉 尹","zpiCode":"708964"}}},{"id":9,"name":{"firstName":"子轩","lastName":"贾"},"info":{"phoneNumber":"936-24773798","address":{"city":"宁 高头市","zpiCode":"114186"}}},{"id":10,"name":{"firstName":"文博","lastName":"夏"},"info":{"phoneNumber":"980-77474759","address":{"city":"珠 徐","zpiCode":"569327"}}},{"id":11,"name":{"firstName":"金鑫","lastName":"洪"},"info":{"phoneNumber":"023-70291178","address":{"city":"珠 洪","zpiCode":"979907"}}},{"id":12,"name":{"firstName":"浩轩","lastName":"赖"},"info":{"phoneNumber":"269-32795074","address":{"city":"明杰门市","zpiCode":"915284"}}},{"id":13,"name":{"firstName":"擎苍","lastName":"程"},"info":{"phoneNumber":"036-93431103","address":{"city":"福 周","zpiCode":"761609"}}},{"id":14,"name":{"firstName":"思","lastName":"邵"},"info":{"phoneNumber":"056-06311549","address":{"city":"谭汉市","zpiCode":"530644"}}},{"id":15,"name":{"firstName":"果","lastName":"胡"},"info":{"phoneNumber":"425-94054422","address":{"city":"包 武","zpiCode":"203737"}}},{"id":16,"name":{"firstName":"煜祺","lastName":"崔"},"info":{"phoneNumber":"461-94702582","address":{"city":"南 方","zpiCode":"663281"}}},{"id":17,"name":{"firstName":"锦程","lastName":"贺"},"info":{"phoneNumber":"298-64212511","address":{"city":"吉 萧","zpiCode":"483268"}}},{"id":18,"name":{"firstName":"思远","lastName":"李"},"info":{"phoneNumber":"813-92922271","address":{"city":"彬口市","zpiCode":"770067"}}},{"id":19,"name":{"firstName":"晓啸","lastName":"赵"},"info":{"phoneNumber":"473-70512189","address":{"city":"成 卢","zpiCode":"420204"}}},{"id":20,"name":{"firstName":"明轩","lastName":"武"},"info":{"phoneNumber":"415-15978808","address":{"city":"武 赖","zpiCode":"254917"}}},{"id":21,"name":{"firstName":"煜城","lastName":"徐"},"info":{"phoneNumber":"369-92663690","address":{"city":"鹏煊京市","zpiCode":"829566"}}},{"id":22,"name":{"firstName":"博涛","lastName":"杜"},"info":{"phoneNumber":"771-99681084","address":{"city":"贵 丁","zpiCode":"619596"}}},{"id":23,"name":{"firstName":"振家","lastName":"薛"},"info":{"phoneNumber":"247-60575124","address":{"city":"太 莫汉市","zpiCode":"325621"}}},{"id":24,"name":{"firstName":"健柏","lastName":"贺"},"info":{"phoneNumber":"302-19239993","address":{"city":"吉 郭安市","zpiCode":"826973"}}},{"id":25,"name":{"firstName":"博涛","lastName":"丁"},"info":{"phoneNumber":"851-49962833","address":{"city":"子默阳市","zpiCode":"026297"}}},{"id":26,"name":{"firstName":"擎苍","lastName":"邓"},"info":{"phoneNumber":"063-60934233","address":{"city":"明哲南市","zpiCode":"516468"}}},{"id":27,"name":{"firstName":"博超","lastName":"尹"},"info":{"phoneNumber":"828-45095433","address":{"city":"熠彤口市","zpiCode":"015899"}}},{"id":28,"name":{"firstName":"明哲","lastName":"袁"},"info":{"phoneNumber":"371-61454083","address":{"city":"陶乡县","zpiCode":"426597"}}},{"id":29,"name":{"firstName":"明哲","lastName":"郝"},"info":{"phoneNumber":"817-45381504","address":{"city":"福 姜林市","zpiCode":"467586"}}},{"id":30,"name":{"firstName":"风华","lastName":"廖"},"info":{"phoneNumber":"571-78319022","address":{"city":"安 张","zpiCode":"471713"}}},{"id":31,"name":{"firstName":"钰轩","lastName":"韦"},"info":{"phoneNumber":"747-54126597","address":{"city":"乐驹码市","zpiCode":"771521"}}},{"id":32,"name":{"firstName":"烨华","lastName":"石"},"info":{"phoneNumber":"085-69645707","address":{"city":"天磊都市","zpiCode":"015720"}}},{"id":33,"name":{"firstName":"绍辉","lastName":"秦"},"info":{"phoneNumber":"743-45124624","address":{"city":"明杰沙市","zpiCode":"593217"}}},{"id":34,"name":{"firstName":"笑愚","lastName":"侯"},"info":{"phoneNumber":"065-89735073","address":{"city":"冯州市","zpiCode":"648844"}}},{"id":35,"name":{"firstName":"擎宇","lastName":"韦"},"info":{"phoneNumber":"652-13852712","address":{"city":"吉 周","zpiCode":"401239"}}},{"id":36,"name":{"firstName":"明杰","lastName":"石"},"info":{"phoneNumber":"819-38875772","address":{"city":"南 陶","zpiCode":"691961"}}},{"id":37,"name":{"firstName":"伟泽","lastName":"钟"},"info":{"phoneNumber":"197-51197395","address":{"city":"智辉林市","zpiCode":"675707"}}},{"id":38,"name":{"firstName":"鹭洋","lastName":"杨"},"info":{"phoneNumber":"279-84072501","address":{"city":"诸 莫","zpiCode":"910671"}}},{"id":39,"name":{"firstName":"乐驹","lastName":"钱"},"info":{"phoneNumber":"808-72265979","address":{"city":"北 彭头市","zpiCode":"544179"}}},{"id":40,"name":{"firstName":"炎彬","lastName":"张"},"info":{"phoneNumber":"931-37603385","address":{"city":"黄原市","zpiCode":"576538"}}},{"id":41,"name":{"firstName":"擎宇","lastName":"阎"},"info":{"phoneNumber":"454-90568059","address":{"city":"衡 龚","zpiCode":"917731"}}},{"id":42,"name":{"firstName":"烨磊","lastName":"贾"},"info":{"phoneNumber":"309-62345885","address":{"city":"成 朱都市","zpiCode":"593269"}}},{"id":43,"name":{"firstName":"黎昕","lastName":"戴"},"info":{"phoneNumber":"104-62666361","address":{"city":"建辉汉市","zpiCode":"461855"}}},{"id":44,"name":{"firstName":"懿轩","lastName":"吕"},"info":{"phoneNumber":"035-37459035","address":{"city":"鹏煊都市","zpiCode":"258331"}}},{"id":45,"name":{"firstName":"明杰","lastName":"赖"},"info":{"phoneNumber":"932-52695458","address":{"city":"吉 卢","zpiCode":"883162"}}},{"id":46,"name":{"firstName":"立轩","lastName":"陶"},"info":{"phoneNumber":"532-32636848","address":{"city":"龙沙市","zpiCode":"041413"}}},{"id":47,"name":{"firstName":"弘文","lastName":"方"},"info":{"phoneNumber":"130-29988266","address":{"city":"夏阳市","zpiCode":"162286"}}},{"id":48,"name":{"firstName":"熠彤","lastName":"邹"},"info":{"phoneNumber":"476-21940635","address":{"city":"尹口市","zpiCode":"510517"}}},{"id":49,"name":{"firstName":"明","lastName":"尹"},"info":{"phoneNumber":"964-27290073","address":{"city":"成 徐","zpiCode":"986128"}}}],"banners":[{"comment":"","title":"北弗里斯兰 · 不如去旅行","url":"https://ooo.0o0.ooo/2017/06/26/59512bbddc037.jpg"},{"comment":"","title":"也许只是承让了","url":"https://ooo.0o0.ooo/2017/06/26/59512bbddc299.jpg"},{"comment":"","title":"人类学研究笔记","url":"https://ooo.0o0.ooo/2017/06/26/59512bbddcccc.jpg"}],"start-image":{"text":"© HaHa","img":"https://ooo.0o0.ooo/2017/06/16/5942e6866f7ef.jpg"},"posts":[[{"title":"sed-ex-quam","img":"http://lorempixel.com/640/480/nature","date":"2017-06-26T16:17:20.974Z"},{"title":"mollitia-nemo-quibusdam","img":"http://lorempixel.com/640/480/nature","date":"2017-06-26T16:17:20.974Z"},{"title":"iusto-dolores-et","img":"http://lorempixel.com/640/480/nature","date":"2017-06-26T16:17:20.974Z"},{"title":"nihil-ipsa-expedita","img":"http://lorempixel.com/640/480/nature","date":"2017-06-26T16:17:20.974Z"},{"title":"amet-ducimus-maxime","img":"http://lorempixel.com/640/480/nature","date":"2017-06-26T16:17:20.974Z"},{"title":"quasi-excepturi-illum","img":"http://lorempixel.com/640/480/nature","date":"2017-06-26T16:17:20.974Z"},{"title":"quis-molestias-ut","img":"http://lorempixel.com/640/480/nature","date":"2017-06-26T16:17:20.974Z"},{"title":"tempora-veritatis-necessitatibus","img":"http://lorempixel.com/640/480/nature","date":"2017-06-26T16:17:20.974Z"},{"title":"eaque-aut-incidunt","img":"http://lorempixel.com/640/480/nature","date":"2017-06-26T16:17:20.974Z"},{"title":"quae-voluptates-sequi","img":"http://lorempixel.com/640/480/nature","date":"2017-06-26T16:17:20.974Z"}],[{"title":"suscipit-id-quaerat","img":"http://lorempixel.com/640/480/nature","date":"2017-06-25T16:17:20.974Z"},{"title":"modi-nam-molestiae","img":"http://lorempixel.com/640/480/nature","date":"2017-06-25T16:17:20.974Z"},{"title":"quasi-aut-fugiat","img":"http://lorempixel.com/640/480/nature","date":"2017-06-25T16:17:20.974Z"},{"title":"et-delectus-facilis","img":"http://lorempixel.com/640/480/nature","date":"2017-06-25T16:17:20.974Z"},{"title":"sed-facere-qui","img":"http://lorempixel.com/640/480/nature","date":"2017-06-25T16:17:20.974Z"},{"title":"impedit-tempore-asperiores","img":"http://lorempixel.com/640/480/nature","date":"2017-06-25T16:17:20.974Z"},{"title":"voluptas-rerum-sint","img":"http://lorempixel.com/640/480/nature","date":"2017-06-25T16:17:20.974Z"},{"title":"molestiae-mollitia-quibusdam","img":"http://lorempixel.com/640/480/nature","date":"2017-06-25T16:17:20.974Z"},{"title":"quibusdam-quis-debitis","img":"http://lorempixel.com/640/480/nature","date":"2017-06-25T16:17:20.974Z"},{"title":"consectetur-quis-unde","img":"http://lorempixel.com/640/480/nature","date":"2017-06-25T16:17:20.974Z"},{"title":"aliquid-voluptatibus-dolorem","img":"http://lorempixel.com/640/480/nature","date":"2017-06-25T16:17:20.974Z"},{"title":"nisi-architecto-architecto","img":"http://lorempixel.com/640/480/nature","date":"2017-06-25T16:17:20.974Z"},{"title":"quos-ipsum-est","img":"http://lorempixel.com/640/480/nature","date":"2017-06-25T16:17:20.974Z"},{"title":"laboriosam-quo-est","img":"http://lorempixel.com/640/480/nature","date":"2017-06-25T16:17:20.974Z"}],[{"title":"in-eligendi-cupiditate","img":"http://lorempixel.com/640/480/nature","date":"2017-06-24T16:17:20.974Z"},{"title":"commodi-ea-quia","img":"http://lorempixel.com/640/480/nature","date":"2017-06-24T16:17:20.974Z"},{"title":"adipisci-sed-aliquam","img":"http://lorempixel.com/640/480/nature","date":"2017-06-24T16:17:20.974Z"},{"title":"consequatur-qui-impedit","img":"http://lorempixel.com/640/480/nature","date":"2017-06-24T16:17:20.974Z"},{"title":"ut-qui-ea","img":"http://lorempixel.com/640/480/nature","date":"2017-06-24T16:17:20.974Z"},{"title":"deserunt-et-nobis","img":"http://lorempixel.com/640/480/nature","date":"2017-06-24T16:17:20.974Z"},{"title":"illum-quidem-animi","img":"http://lorempixel.com/640/480/nature","date":"2017-06-24T16:17:20.974Z"},{"title":"ab-aliquam-qui","img":"http://lorempixel.com/640/480/nature","date":"2017-06-24T16:17:20.974Z"},{"title":"debitis-incidunt-aut","img":"http://lorempixel.com/640/480/nature","date":"2017-06-24T16:17:20.974Z"},{"title":"harum-recusandae-qui","img":"http://lorempixel.com/640/480/nature","date":"2017-06-24T16:17:20.974Z"},{"title":"in-voluptatum-voluptatem","img":"http://lorempixel.com/640/480/nature","date":"2017-06-24T16:17:20.974Z"}],[{"title":"ad-nihil-et","img":"http://lorempixel.com/640/480/nature","date":"2017-06-23T16:17:20.974Z"},{"title":"et-necessitatibus-ipsa","img":"http://lorempixel.com/640/480/nature","date":"2017-06-23T16:17:20.974Z"},{"title":"ipsa-aut-in","img":"http://lorempixel.com/640/480/nature","date":"2017-06-23T16:17:20.974Z"},{"title":"sed-consequatur-et","img":"http://lorempixel.com/640/480/nature","date":"2017-06-23T16:17:20.974Z"},{"title":"harum-ullam-quia","img":"http://lorempixel.com/640/480/nature","date":"2017-06-23T16:17:20.974Z"},{"title":"id-tempore-non","img":"http://lorempixel.com/640/480/nature","date":"2017-06-23T16:17:20.974Z"},{"title":"corporis-optio-est","img":"http://lorempixel.com/640/480/nature","date":"2017-06-23T16:17:20.974Z"},{"title":"totam-et-deleniti","img":"http://lorempixel.com/640/480/nature","date":"2017-06-23T16:17:20.974Z"},{"title":"tenetur-est-voluptate","img":"http://lorempixel.com/640/480/nature","date":"2017-06-23T16:17:20.974Z"},{"title":"aut-est-veritatis","img":"http://lorempixel.com/640/480/nature","date":"2017-06-23T16:17:20.974Z"},{"title":"placeat-ut-qui","img":"http://lorempixel.com/640/480/nature","date":"2017-06-23T16:17:20.974Z"},{"title":"aut-voluptatem-perferendis","img":"http://lorempixel.com/640/480/nature","date":"2017-06-23T16:17:20.974Z"}],[{"title":"aut-eum-tempore","img":"http://lorempixel.com/640/480/nature","date":"2017-06-22T16:17:20.974Z"},{"title":"iusto-consequuntur-aut","img":"http://lorempixel.com/640/480/nature","date":"2017-06-22T16:17:20.974Z"},{"title":"quia-cum-autem","img":"http://lorempixel.com/640/480/nature","date":"2017-06-22T16:17:20.974Z"},{"title":"rerum-voluptatem-non","img":"http://lorempixel.com/640/480/nature","date":"2017-06-22T16:17:20.974Z"},{"title":"est-iure-temporibus","img":"http://lorempixel.com/640/480/nature","date":"2017-06-22T16:17:20.974Z"},{"title":"enim-maiores-et","img":"http://lorempixel.com/640/480/nature","date":"2017-06-22T16:17:20.974Z"},{"title":"tenetur-dolorum-neque","img":"http://lorempixel.com/640/480/nature","date":"2017-06-22T16:17:20.974Z"},{"title":"officia-aut-illo","img":"http://lorempixel.com/640/480/nature","date":"2017-06-22T16:17:20.974Z"},{"title":"quis-odit-non","img":"http://lorempixel.com/640/480/nature","date":"2017-06-22T16:17:20.974Z"},{"title":"nihil-modi-voluptas","img":"http://lorempixel.com/640/480/nature","date":"2017-06-22T16:17:20.974Z"},{"title":"ratione-non-similique","img":"http://lorempixel.com/640/480/nature","date":"2017-06-22T16:17:20.974Z"},{"title":"quam-dolorem-molestias","img":"http://lorempixel.com/640/480/nature","date":"2017-06-22T16:17:20.974Z"}]]}
